verilog/uart/rx.v
module rx (
    input clk,
    input rst,
    input rx_tick,
    input read_clear,
    input rx,
    output ready,
    output [7:0] data_out
);

localparam [2:0] 
    RX_IDLE  = 3'd0,
    RX_START = 3'd1,
    RX_DATA  = 3'd2,
    RX_STOP  = 3'd3,
    RX_ERROR = 3'd4;

reg start_valid = 1'b0;
reg stop_valid = 1'b0;
reg [2:0] rx_state = RX_IDLE;
reg [3:0] rx_tick_cnt = 4'd0;
reg rx_sync_1 = 1'b1;
reg rx_sync_2 = 1'b1;

reg [2:0] sampling = 3'd0;
reg [3:0] data_cnt = 4'd0;
reg [7:0] data = 8'd0;
reg ready_reg = 1'b0;

assign ready = ready_reg;
assign data_out = data;

// Synchronizer to prevent metastability
always @(posedge clk) begin
    rx_sync_1 <= rx;
    rx_sync_2 <= rx_sync_1;
end

// Main FSM
always @(posedge clk) begin
    if (rst) begin
        rx_state    <= RX_IDLE;
        rx_tick_cnt <= 4'd0;
        data_cnt    <= 4'd0;
        sampling    <= 3'd0;
        start_valid <= 1'b0;
        stop_valid  <= 1'b0;
        ready_reg   <= 1'b0;
    end else begin
        // Ready clear flag logic
        if (read_clear) begin
            ready_reg <= 1'b0;
        end

        case (rx_state)

            RX_IDLE: begin
                start_valid <= 1'b0;
                stop_valid  <= 1'b0;
                rx_tick_cnt <= 4'd0;
                data_cnt    <= 4'd0;
                if (!rx_sync_2) begin
                    rx_state <= RX_START;
                end
            end

            RX_START: begin
                if (rx_tick) begin
                    rx_tick_cnt <= rx_tick_cnt + 4'd1;
                    
                    // Sample start bit at midpoint tick 7
                    if (rx_tick_cnt == 4'd7) begin
                        if (!rx_sync_2) begin
                            start_valid <= 1'b1;
                        end
                    end

if (rx_tick_cnt == 4'd15) begin
    if (start_valid) begin
        rx_state    <= RX_DATA;
        sampling    <= 3'd0;
        data_cnt    <= 4'd0;
        rx_tick_cnt <= 4'd0; // Explicitly reset tick counter for bit 0
    end else begin
        rx_state    <= RX_IDLE;
    end
end
                end
            end

            RX_DATA: begin
                if (rx_tick) begin
                    rx_tick_cnt <= rx_tick_cnt + 4'd1;

                    // 5-sample majority voting window
                    if (rx_tick_cnt == 4'd6)  sampling <= sampling + rx_sync_2;
                    if (rx_tick_cnt == 4'd7)  sampling <= sampling + rx_sync_2;
                    if (rx_tick_cnt == 4'd8)  sampling <= sampling + rx_sync_2;
                    if (rx_tick_cnt == 4'd9)  sampling <= sampling + rx_sync_2;
                    if (rx_tick_cnt == 4'd10) sampling <= sampling + rx_sync_2;

                    if (rx_tick_cnt == 4'd15) begin
                        // LSB-first shift register logic
                        if (sampling >= 3'd3) begin
                            data <= {1'b1, data[7:1]};
                        end else begin
                            data <= {1'b0, data[7:1]};
                        end

                        data_cnt <= data_cnt + 4'd1;
                        sampling <= 3'd0;

                        if (data_cnt == 4'd7) begin
                            rx_state <= RX_STOP;
                        end
                    end
                end
            end

            RX_STOP: begin
                if (rx_tick) begin
                    rx_tick_cnt <= rx_tick_cnt + 4'd1;

                    // Check stop bit line status at midpoint tick 7
                    if (rx_tick_cnt == 4'd7) begin
                        if (rx_sync_2) begin
                            stop_valid <= 1'b1;
                        end
                    end

                    if (rx_tick_cnt == 4'd15) begin
                        if (stop_valid) begin
                            rx_state  <= RX_IDLE;
                            ready_reg <= 1'b1;
                        end else begin
                            rx_state <= RX_ERROR;
                        end
                    end
                end
            end

RX_ERROR: begin
    if (rx_tick) begin
        rx_tick_cnt <= rx_tick_cnt + 4'd1;
        // Only return to IDLE once the RX line goes back HIGH (idle state)
        if (rx_tick_cnt == 4'd15 && rx_sync_2) begin
            rx_state <= RX_IDLE;
        end
    end
end

            default: rx_state <= RX_IDLE;

        endcase
    end
end

endmodule

verilog/uart/tb/tb_rx.v
`timescale 1ns / 1ps

module tb_rx;

    // Inputs
    reg clk;
    reg rst;
    reg rx_tick;
    reg read_clear;
    reg rx;

    // Outputs
    wire ready;
    wire [7:0] data_out;

    // Clock definitions (100 MHz main clock)
    parameter CLK_PERIOD = 10; 
    
    // Instantiate Unit Under Test (UUT)
    rx uut (
        .clk(clk),
        .rst(rst),
        .rx_tick(rx_tick),
        .read_clear(read_clear),
        .rx(rx),
        .ready(ready),
        .data_out(data_out)
    );

    // Clock generation
    always #(CLK_PERIOD / 2) clk = ~clk;

    // Continuous rx_tick generator (oversampling clock)
    // Runs 16 times faster than the baud rate pulse needed for bit processing
    always begin
        #(CLK_PERIOD * 4);
        rx_tick = 1'b1;
        #(CLK_PERIOD);
        rx_tick = 1'b0;
    end

    // Task to send 1 byte over RX with 16 ticks per bit
    task send_uart_byte(input [7:0] byte_to_send);
        integer i, t;
        begin
            // Start Bit (LOW)
            rx = 1'b0;
            for (t = 0; t < 16; t = t + 1) @(posedge rx_tick);

            // Data Bits (LSB First)
            for (i = 0; i < 8; i = i + 1) begin
                rx = byte_to_send[i];
                for (t = 0; t < 16; t = t + 1) @(posedge rx_tick);
            end

            // Stop Bit (HIGH)
            rx = 1'b1;
            for (t = 0; t < 16; t = t + 1) @(posedge rx_tick);
        end
    endtask

    // Main Test Stimulus
    initial begin
        // Waveform dumping for GTKWave / ModelSim / Icarus
        $dumpfile("rx_waveform.vcd");
        $dumpvars(0, tb_rx);

        // Initial state
        clk = 1'b0;
        rst = 1'b1;
        rx_tick = 1'b0;
        read_clear = 1'b0;
        rx = 1'b1; // Idle state is HIGH

        // Apply Reset
        #(CLK_PERIOD * 10);
        rst = 1'b0;
        #(CLK_PERIOD * 10);

        // --- TEST 1: Transmit Valid Byte 0xA5 (10100101) ---
        $display("[%0t ns] Test 1: Sending 0xA5...", $time);
        send_uart_byte(8'hA5);

        // Wait for ready flag
        wait(ready == 1'b1);
        $display("[%0t ns] Received: 0x%h (Expected: 0xA5)", $time, data_out);
        
        if (data_out === 8'hA5) $display("--> TEST 1 PASSED");
        else $display("--> TEST 1 FAILED");

        // Clear Ready flag
        #(CLK_PERIOD * 5);
        read_clear = 1'b1;
        #(CLK_PERIOD);
        read_clear = 1'b0;
        #(CLK_PERIOD * 10);

        // --- TEST 2: Transmit Valid Byte 0x3C (00111100) ---
        $display("[%0t ns] Test 2: Sending 0x3C...", $time);
        send_uart_byte(8'h3C);

        wait(ready == 1'b1);
        $display("[%0t ns] Received: 0x%h (Expected: 0x3C)", $time, data_out);

        if (data_out === 8'h3C) $display("--> TEST 2 PASSED");
        else $display("--> TEST 2 FAILED");

        // Clear Ready flag
        #(CLK_PERIOD * 5);
        read_clear = 1'b1;
        #(CLK_PERIOD);
        read_clear = 1'b0;
        #(CLK_PERIOD * 20);

        $display("[%0t ns] Simulation Complete.", $time);
        $finish;
    end

endmodule

verilog/uart/rx_waveform.vcd
$date
	Mon Sep 21 08:11:23 2026
$end
$version
	Icarus Verilog
$end
$timescale
	1ps
$end
$scope module tb_rx $end
$var wire 1 ! ready $end
$var wire 8 " data_out [7:0] $end
$var parameter 32 # CLK_PERIOD $end
$var reg 1 $ clk $end
$var reg 1 % read_clear $end
$var reg 1 & rst $end
$var reg 1 ' rx $end
$var reg 1 ( rx_tick $end
$scope module uut $end
$var wire 1 $ clk $end
$var wire 8 ) data_out [7:0] $end
$var wire 1 % read_clear $end
$var wire 1 ! ready $end
$var wire 1 & rst $end
$var wire 1 ' rx $end
$var wire 1 ( rx_tick $end
$var parameter 3 * RX_DATA $end
$var parameter 3 + RX_ERROR $end
$var parameter 3 , RX_IDLE $end
$var parameter 3 - RX_START $end
$var parameter 3 . RX_STOP $end
$var reg 8 / data [7:0] $end
$var reg 4 0 data_cnt [3:0] $end
$var reg 1 1 ready_reg $end
$var reg 3 2 rx_state [2:0] $end
$var reg 1 3 rx_sync_1 $end
$var reg 1 4 rx_sync_2 $end
$var reg 4 5 rx_tick_cnt [3:0] $end
$var reg 3 6 sampling [2:0] $end
$var reg 1 7 start_valid $end
$var reg 1 8 stop_valid $end
$upscope $end
$scope task send_uart_byte $end
$var reg 8 9 byte_to_send [7:0] $end
$var integer 32 : i [31:0] $end
$var integer 32 ; t [31:0] $end
$upscope $end
$upscope $end
$enddefinitions $end
$comment Show the parameter values. $end
$dumpall
b11 .
b1 -
b0 ,
b100 +
b10 *
b1010 #
$end
#0
$dumpvars
bx ;
bx :
bx 9
08
07
b0 6
b0 5
14
13
b0 2
01
b0 0
b0 /
b0 )
0(
1'
1&
0%
0$
b0 "
0!
$end
#5000
1$
#10000
0$
#15000
1$
#20000
0$
#25000
1$
#30000
0$
#35000
1$
#40000
0$
1(
#45000
1$
#50000
0$
0(
#55000
1$
#60000
0$
#65000
1$
#70000
0$
#75000
1$
#80000
0$
#85000
1$
#90000
0$
1(
#95000
1$
#100000
0$
0(
0&
#105000
1$
#110000
0$
#115000
1$
#120000
0$
#125000
1$
#130000
0$
#135000
1$
#140000
0$
1(
#145000
1$
#150000
0$
0(
#155000
1$
#160000
0$
#165000
1$
#170000
0$
#175000
1$
#180000
0$
#185000
1$
#190000
0$
1(
#195000
1$
#200000
0$
0(
b0 ;
0'
b10100101 9
#205000
03
1$
#210000
0$
#215000
04
1$
#220000
0$
#225000
b1 2
1$
#230000
0$
#235000
1$
#240000
b1 ;
0$
1(
#245000
b1 5
1$
#250000
0$
0(
#255000
1$
#260000
0$
#265000
1$
#270000
0$
#275000
1$
#280000
0$
#285000
1$
#290000
b10 ;
0$
1(
#295000
b10 5
1$
#300000
0$
0(
#305000
1$
#310000
0$
#315000
1$
#320000
0$
#325000
1$
#330000
0$
#335000
1$
#340000
b11 ;
0$
1(
#345000
b11 5
1$
#350000
0$
0(
#355000
1$
#360000
0$
#365000
1$
#370000
0$
#375000
1$
#380000
0$
#385000
1$
#390000
b100 ;
0$
1(
#395000
b100 5
1$
#400000
0$
0(
#405000
1$
#410000
0$
#415000
1$
#420000
0$
#425000
1$
#430000
0$
#435000
1$
#440000
b101 ;
0$
1(
#445000
b101 5
1$
#450000
0$
0(
#455000
1$
#460000
0$
#465000
1$
#470000
0$
#475000
1$
#480000
0$
#485000
1$
#490000
b110 ;
0$
1(
#495000
b110 5
1$
#500000
0$
0(
#505000
1$
#510000
0$
#515000
1$
#520000
0$
#525000
1$
#530000
0$
#535000
1$
#540000
b111 ;
0$
1(
#545000
b111 5
1$
#550000
0$
0(
#555000
1$
#560000
0$
#565000
1$
#570000
0$
#575000
1$
#580000
0$
#585000
1$
#590000
b1000 ;
0$
1(
#595000
17
b1000 5
1$
#600000
0$
0(
#605000
1$
#610000
0$
#615000
1$
#620000
0$
#625000
1$
#630000
0$
#635000
1$
#640000
b1001 ;
0$
1(
#645000
b1001 5
1$
#650000
0$
0(
#655000
1$
#660000
0$
#665000
1$
#670000
0$
#675000
1$
#680000
0$
#685000
1$
#690000
b1010 ;
0$
1(
#695000
b1010 5
1$
#700000
0$
0(
#705000
1$
#710000
0$
#715000
1$
#720000
0$
#725000
1$
#730000
0$
#735000
1$
#740000
b1011 ;
0$
1(
#745000
b1011 5
1$
#750000
0$
0(
#755000
1$
#760000
0$
#765000
1$
#770000
0$
#775000
1$
#780000
0$
#785000
1$
#790000
b1100 ;
0$
1(
#795000
b1100 5
1$
#800000
0$
0(
#805000
1$
#810000
0$
#815000
1$
#820000
0$
#825000
1$
#830000
0$
#835000
1$
#840000
b1101 ;
0$
1(
#845000
b1101 5
1$
#850000
0$
0(
#855000
1$
#860000
0$
#865000
1$
#870000
0$
#875000
1$
#880000
0$
#885000
1$
#890000
b1110 ;
0$
1(
#895000
b1110 5
1$
#900000
0$
0(
#905000
1$
#910000
0$
#915000
1$
#920000
0$
#925000
1$
#930000
0$
#935000
1$
#940000
b1111 ;
0$
1(
#945000
b1111 5
1$
#950000
0$
0(
#955000
1$
#960000
0$
#965000
1$
#970000
0$
#975000
1$
#980000
0$
#985000
1$
#990000
1'
b0 :
b0 ;
0$
1(
#995000
b10 2
b0 5
13
1$
#1000000
0$
0(
#1005000
14
1$
#1010000
0$
#1015000
1$
#1020000
0$
#1025000
1$
#1030000
0$
#1035000
1$
#1040000
b1 ;
0$
1(
#1045000
b1 5
1$
#1050000
0$
0(
#1055000
1$
#1060000
0$
#1065000
1$
#1070000
0$
#1075000
1$
#1080000
0$
#1085000
1$
#1090000
b10 ;
0$
1(
#1095000
b10 5
1$
#1100000
0$
0(
#1105000
1$
#1110000
0$
#1115000
1$
#1120000
0$
#1125000
1$
#1130000
0$
#1135000
1$
#1140000
b11 ;
0$
1(
#1145000
b11 5
1$
#1150000
0$
0(
#1155000
1$
#1160000
0$
#1165000
1$
#1170000
0$
#1175000
1$
#1180000
0$
#1185000
1$
#1190000
b100 ;
0$
1(
#1195000
b100 5
1$
#1200000
0$
0(
#1205000
1$
#1210000
0$
#1215000
1$
#1220000
0$
#1225000
1$
#1230000
0$
#1235000
1$
#1240000
b101 ;
0$
1(
#1245000
b101 5
1$
#1250000
0$
0(
#1255000
1$
#1260000
0$
#1265000
1$
#1270000
0$
#1275000
1$
#1280000
0$
#1285000
1$
#1290000
b110 ;
0$
1(
#1295000
b110 5
1$
#1300000
0$
0(
#1305000
1$
#1310000
0$
#1315000
1$
#1320000
0$
#1325000
1$
#1330000
0$
#1335000
1$
#1340000
b111 ;
0$
1(
#1345000
b1 6
b111 5
1$
#1350000
0$
0(
#1355000
1$
#1360000
0$
#1365000
1$
#1370000
0$
#1375000
1$
#1380000
0$
#1385000
1$
#1390000
b1000 ;
0$
1(
#1395000
b10 6
b1000 5
1$
#1400000
0$
0(
#1405000
1$
#1410000
0$
#1415000
1$
#1420000
0$
#1425000
1$
#1430000
0$
#1435000
1$
#1440000
b1001 ;
0$
1(
#1445000
b11 6
b1001 5
1$
#1450000
0$
0(
#1455000
1$
#1460000
0$
#1465000
1$
#1470000
0$
#1475000
1$
#1480000
0$
#1485000
1$
#1490000
b1010 ;
0$
1(
#1495000
b100 6
b1010 5
1$
#1500000
0$
0(
#1505000
1$
#1510000
0$
#1515000
1$
#1520000
0$
#1525000
1$
#1530000
0$
#1535000
1$
#1540000
b1011 ;
0$
1(
#1545000
b101 6
b1011 5
1$
#1550000
0$
0(
#1555000
1$
#1560000
0$
#1565000
1$
#1570000
0$
#1575000
1$
#1580000
0$
#1585000
1$
#1590000
b1100 ;
0$
1(
#1595000
b1100 5
1$
#1600000
0$
0(
#1605000
1$
#1610000
0$
#1615000
1$
#1620000
0$
#1625000
1$
#1630000
0$
#1635000
1$
#1640000
b1101 ;
0$
1(
#1645000
b1101 5
1$
#1650000
0$
0(
#1655000
1$
#1660000
0$
#1665000
1$
#1670000
0$
#1675000
1$
#1680000
0$
#1685000
1$
#1690000
b1110 ;
0$
1(
#1695000
b1110 5
1$
#1700000
0$
0(
#1705000
1$
#1710000
0$
#1715000
1$
#1720000
0$
#1725000
1$
#1730000
0$
#1735000
1$
#1740000
b1111 ;
0$
1(
#1745000
b1111 5
1$
#1750000
0$
0(
#1755000
1$
#1760000
0$
#1765000
1$
#1770000
0$
#1775000
1$
#1780000
0$
#1785000
1$
#1790000
0'
b1 :
b0 ;
0$
1(
#1795000
b0 6
b1 0
b10000000 "
b10000000 )
b10000000 /
b0 5
03
1$
#1800000
0$
0(
#1805000
04
1$
#1810000
0$
#1815000
1$
#1820000
0$
#1825000
1$
#1830000
0$
#1835000
1$
#1840000
b1 ;
0$
1(
#1845000
b1 5
1$
#1850000
0$
0(
#1855000
1$
#1860000
0$
#1865000
1$
#1870000
0$
#1875000
1$
#1880000
0$
#1885000
1$
#1890000
b10 ;
0$
1(
#1895000
b10 5
1$
#1900000
0$
0(
#1905000
1$
#1910000
0$
#1915000
1$
#1920000
0$
#1925000
1$
#1930000
0$
#1935000
1$
#1940000
b11 ;
0$
1(
#1945000
b11 5
1$
#1950000
0$
0(
#1955000
1$
#1960000
0$
#1965000
1$
#1970000
0$
#1975000
1$
#1980000
0$
#1985000
1$
#1990000
b100 ;
0$
1(
#1995000
b100 5
1$
#2000000
0$
0(
#2005000
1$
#2010000
0$
#2015000
1$
#2020000
0$
#2025000
1$
#2030000
0$
#2035000
1$
#2040000
b101 ;
0$
1(
#2045000
b101 5
1$
#2050000
0$
0(
#2055000
1$
#2060000
0$
#2065000
1$
#2070000
0$
#2075000
1$
#2080000
0$
#2085000
1$
#2090000
b110 ;
0$
1(
#2095000
b110 5
1$
#2100000
0$
0(
#2105000
1$
#2110000
0$
#2115000
1$
#2120000
0$
#2125000
1$
#2130000
0$
#2135000
1$
#2140000
b111 ;
0$
1(
#2145000
b111 5
1$
#2150000
0$
0(
#2155000
1$
#2160000
0$
#2165000
1$
#2170000
0$
#2175000
1$
#2180000
0$
#2185000
1$
#2190000
b1000 ;
0$
1(
#2195000
b1000 5
1$
#2200000
0$
0(
#2205000
1$
#2210000
0$
#2215000
1$
#2220000
0$
#2225000
1$
#2230000
0$
#2235000
1$
#2240000
b1001 ;
0$
1(
#2245000
b1001 5
1$
#2250000
0$
0(
#2255000
1$
#2260000
0$
#2265000
1$
#2270000
0$
#2275000
1$
#2280000
0$
#2285000
1$
#2290000
b1010 ;
0$
1(
#2295000
b1010 5
1$
#2300000
0$
0(
#2305000
1$
#2310000
0$
#2315000
1$
#2320000
0$
#2325000
1$
#2330000
0$
#2335000
1$
#2340000
b1011 ;
0$
1(
#2345000
b1011 5
1$
#2350000
0$
0(
#2355000
1$
#2360000
0$
#2365000
1$
#2370000
0$
#2375000
1$
#2380000
0$
#2385000
1$
#2390000
b1100 ;
0$
1(
#2395000
b1100 5
1$
#2400000
0$
0(
#2405000
1$
#2410000
0$
#2415000
1$
#2420000
0$
#2425000
1$
#2430000
0$
#2435000
1$
#2440000
b1101 ;
0$
1(
#2445000
b1101 5
1$
#2450000
0$
0(
#2455000
1$
#2460000
0$
#2465000
1$
#2470000
0$
#2475000
1$
#2480000
0$
#2485000
1$
#2490000
b1110 ;
0$
1(
#2495000
b1110 5
1$
#2500000
0$
0(
#2505000
1$
#2510000
0$
#2515000
1$
#2520000
0$
#2525000
1$
#2530000
0$
#2535000
1$
#2540000
b1111 ;
0$
1(
#2545000
b1111 5
1$
#2550000
0$
0(
#2555000
1$
#2560000
0$
#2565000
1$
#2570000
0$
#2575000
1$
#2580000
0$
#2585000
1$
#2590000
1'
b10 :
b0 ;
0$
1(
#2595000
b10 0
b1000000 "
b1000000 )
b1000000 /
b0 5
13
1$
#2600000
0$
0(
#2605000
14
1$
#2610000
0$
#2615000
1$
#2620000
0$
#2625000
1$
#2630000
0$
#2635000
1$
#2640000
b1 ;
0$
1(
#2645000
b1 5
1$
#2650000
0$
0(
#2655000
1$
#2660000
0$
#2665000
1$
#2670000
0$
#2675000
1$
#2680000
0$
#2685000
1$
#2690000
b10 ;
0$
1(
#2695000
b10 5
1$
#2700000
0$
0(
#2705000
1$
#2710000
0$
#2715000
1$
#2720000
0$
#2725000
1$
#2730000
0$
#2735000
1$
#2740000
b11 ;
0$
1(
#2745000
b11 5
1$
#2750000
0$
0(
#2755000
1$
#2760000
0$
#2765000
1$
#2770000
0$
#2775000
1$
#2780000
0$
#2785000
1$
#2790000
b100 ;
0$
1(
#2795000
b100 5
1$
#2800000
0$
0(
#2805000
1$
#2810000
0$
#2815000
1$
#2820000
0$
#2825000
1$
#2830000
0$
#2835000
1$
#2840000
b101 ;
0$
1(
#2845000
b101 5
1$
#2850000
0$
0(
#2855000
1$
#2860000
0$
#2865000
1$
#2870000
0$
#2875000
1$
#2880000
0$
#2885000
1$
#2890000
b110 ;
0$
1(
#2895000
b110 5
1$
#2900000
0$
0(
#2905000
1$
#2910000
0$
#2915000
1$
#2920000
0$
#2925000
1$
#2930000
0$
#2935000
1$
#2940000
b111 ;
0$
1(
#2945000
b1 6
b111 5
1$
#2950000
0$
0(
#2955000
1$
#2960000
0$
#2965000
1$
#2970000
0$
#2975000
1$
#2980000
0$
#2985000
1$
#2990000
b1000 ;
0$
1(
#2995000
b10 6
b1000 5
1$
#3000000
0$
0(
#3005000
1$
#3010000
0$
#3015000
1$
#3020000
0$
#3025000
1$
#3030000
0$
#3035000
1$
#3040000
b1001 ;
0$
1(
#3045000
b11 6
b1001 5
1$
#3050000
0$
0(
#3055000
1$
#3060000
0$
#3065000
1$
#3070000
0$
#3075000
1$
#3080000
0$
#3085000
1$
#3090000
b1010 ;
0$
1(
#3095000
b100 6
b1010 5
1$
#3100000
0$
0(
#3105000
1$
#3110000
0$
#3115000
1$
#3120000
0$
#3125000
1$
#3130000
0$
#3135000
1$
#3140000
b1011 ;
0$
1(
#3145000
b101 6
b1011 5
1$
#3150000
0$
0(
#3155000
1$
#3160000
0$
#3165000
1$
#3170000
0$
#3175000
1$
#3180000
0$
#3185000
1$
#3190000
b1100 ;
0$
1(
#3195000
b1100 5
1$
#3200000
0$
0(
#3205000
1$
#3210000
0$
#3215000
1$
#3220000
0$
#3225000
1$
#3230000
0$
#3235000
1$
#3240000
b1101 ;
0$
1(
#3245000
b1101 5
1$
#3250000
0$
0(
#3255000
1$
#3260000
0$
#3265000
1$
#3270000
0$
#3275000
1$
#3280000
0$
#3285000
1$
#3290000
b1110 ;
0$
1(
#3295000
b1110 5
1$
#3300000
0$
0(
#3305000
1$
#3310000
0$
#3315000
1$
#3320000
0$
#3325000
1$
#3330000
0$
#3335000
1$
#3340000
b1111 ;
0$
1(
#3345000
b1111 5
1$
#3350000
0$
0(
#3355000
1$
#3360000
0$
#3365000
1$
#3370000
0$
#3375000
1$
#3380000
0$
#3385000
1$
#3390000
0'
b11 :
b0 ;
0$
1(
#3395000
b0 6
b11 0
b10100000 "
b10100000 )
b10100000 /
b0 5
03
1$
#3400000
0$
0(
#3405000
04
1$
#3410000
0$
#3415000
1$
#3420000
0$
#3425000
1$
#3430000
0$
#3435000
1$
#3440000
b1 ;
0$
1(
#3445000
b1 5
1$
#3450000
0$
0(
#3455000
1$
#3460000
0$
#3465000
1$
#3470000
0$
#3475000
1$
#3480000
0$
#3485000
1$
#3490000
b10 ;
0$
1(
#3495000
b10 5
1$
#3500000
0$
0(
#3505000
1$
#3510000
0$
#3515000
1$
#3520000
0$
#3525000
1$
#3530000
0$
#3535000
1$
#3540000
b11 ;
0$
1(
#3545000
b11 5
1$
#3550000
0$
0(
#3555000
1$
#3560000
0$
#3565000
1$
#3570000
0$
#3575000
1$
#3580000
0$
#3585000
1$
#3590000
b100 ;
0$
1(
#3595000
b100 5
1$
#3600000
0$
0(
#3605000
1$
#3610000
0$
#3615000
1$
#3620000
0$
#3625000
1$
#3630000
0$
#3635000
1$
#3640000
b101 ;
0$
1(
#3645000
b101 5
1$
#3650000
0$
0(
#3655000
1$
#3660000
0$
#3665000
1$
#3670000
0$
#3675000
1$
#3680000
0$
#3685000
1$
#3690000
b110 ;
0$
1(
#3695000
b110 5
1$
#3700000
0$
0(
#3705000
1$
#3710000
0$
#3715000
1$
#3720000
0$
#3725000
1$
#3730000
0$
#3735000
1$
#3740000
b111 ;
0$
1(
#3745000
b111 5
1$
#3750000
0$
0(
#3755000
1$
#3760000
0$
#3765000
1$
#3770000
0$
#3775000
1$
#3780000
0$
#3785000
1$
#3790000
b1000 ;
0$
1(
#3795000
b1000 5
1$
#3800000
0$
0(
#3805000
1$
#3810000
0$
#3815000
1$
#3820000
0$
#3825000
1$
#3830000
0$
#3835000
1$
#3840000
b1001 ;
0$
1(
#3845000
b1001 5
1$
#3850000
0$
0(
#3855000
1$
#3860000
0$
#3865000
1$
#3870000
0$
#3875000
1$
#3880000
0$
#3885000
1$
#3890000
b1010 ;
0$
1(
#3895000
b1010 5
1$
#3900000
0$
0(
#3905000
1$
#3910000
0$
#3915000
1$
#3920000
0$
#3925000
1$
#3930000
0$
#3935000
1$
#3940000
b1011 ;
0$
1(
#3945000
b1011 5
1$
#3950000
0$
0(
#3955000
1$
#3960000
0$
#3965000
1$
#3970000
0$
#3975000
1$
#3980000
0$
#3985000
1$
#3990000
b1100 ;
0$
1(
#3995000
b1100 5
1$
#4000000
0$
0(
#4005000
1$
#4010000
0$
#4015000
1$
#4020000
0$
#4025000
1$
#4030000
0$
#4035000
1$
#4040000
b1101 ;
0$
1(
#4045000
b1101 5
1$
#4050000
0$
0(
#4055000
1$
#4060000
0$
#4065000
1$
#4070000
0$
#4075000
1$
#4080000
0$
#4085000
1$
#4090000
b1110 ;
0$
1(
#4095000
b1110 5
1$
#4100000
0$
0(
#4105000
1$
#4110000
0$
#4115000
1$
#4120000
0$
#4125000
1$
#4130000
0$
#4135000
1$
#4140000
b1111 ;
0$
1(
#4145000
b1111 5
1$
#4150000
0$
0(
#4155000
1$
#4160000
0$
#4165000
1$
#4170000
0$
#4175000
1$
#4180000
0$
#4185000
1$
#4190000
b100 :
b0 ;
0$
1(
#4195000
b100 0
b1010000 "
b1010000 )
b1010000 /
b0 5
1$
#4200000
0$
0(
#4205000
1$
#4210000
0$
#4215000
1$
#4220000
0$
#4225000
1$
#4230000
0$
#4235000
1$
#4240000
b1 ;
0$
1(
#4245000
b1 5
1$
#4250000
0$
0(
#4255000
1$
#4260000
0$
#4265000
1$
#4270000
0$
#4275000
1$
#4280000
0$
#4285000
1$
#4290000
b10 ;
0$
1(
#4295000
b10 5
1$
#4300000
0$
0(
#4305000
1$
#4310000
0$
#4315000
1$
#4320000
0$
#4325000
1$
#4330000
0$
#4335000
1$
#4340000
b11 ;
0$
1(
#4345000
b11 5
1$
#4350000
0$
0(
#4355000
1$
#4360000
0$
#4365000
1$
#4370000
0$
#4375000
1$
#4380000
0$
#4385000
1$
#4390000
b100 ;
0$
1(
#4395000
b100 5
1$
#4400000
0$
0(
#4405000
1$
#4410000
0$
#4415000
1$
#4420000
0$
#4425000
1$
#4430000
0$
#4435000
1$
#4440000
b101 ;
0$
1(
#4445000
b101 5
1$
#4450000
0$
0(
#4455000
1$
#4460000
0$
#4465000
1$
#4470000
0$
#4475000
1$
#4480000
0$
#4485000
1$
#4490000
b110 ;
0$
1(
#4495000
b110 5
1$
#4500000
0$
0(
#4505000
1$
#4510000
0$
#4515000
1$
#4520000
0$
#4525000
1$
#4530000
0$
#4535000
1$
#4540000
b111 ;
0$
1(
#4545000
b111 5
1$
#4550000
0$
0(
#4555000
1$
#4560000
0$
#4565000
1$
#4570000
0$
#4575000
1$
#4580000
0$
#4585000
1$
#4590000
b1000 ;
0$
1(
#4595000
b1000 5
1$
#4600000
0$
0(
#4605000
1$
#4610000
0$
#4615000
1$
#4620000
0$
#4625000
1$
#4630000
0$
#4635000
1$
#4640000
b1001 ;
0$
1(
#4645000
b1001 5
1$
#4650000
0$
0(
#4655000
1$
#4660000
0$
#4665000
1$
#4670000
0$
#4675000
1$
#4680000
0$
#4685000
1$
#4690000
b1010 ;
0$
1(
#4695000
b1010 5
1$
#4700000
0$
0(
#4705000
1$
#4710000
0$
#4715000
1$
#4720000
0$
#4725000
1$
#4730000
0$
#4735000
1$
#4740000
b1011 ;
0$
1(
#4745000
b1011 5
1$
#4750000
0$
0(
#4755000
1$
#4760000
0$
#4765000
1$
#4770000
0$
#4775000
1$
#4780000
0$
#4785000
1$
#4790000
b1100 ;
0$
1(
#4795000
b1100 5
1$
#4800000
0$
0(
#4805000
1$
#4810000
0$
#4815000
1$
#4820000
0$
#4825000
1$
#4830000
0$
#4835000
1$
#4840000
b1101 ;
0$
1(
#4845000
b1101 5
1$
#4850000
0$
0(
#4855000
1$
#4860000
0$
#4865000
1$
#4870000
0$
#4875000
1$
#4880000
0$
#4885000
1$
#4890000
b1110 ;
0$
1(
#4895000
b1110 5
1$
#4900000
0$
0(
#4905000
1$
#4910000
0$
#4915000
1$
#4920000
0$
#4925000
1$
#4930000
0$
#4935000
1$
#4940000
b1111 ;
0$
1(
#4945000
b1111 5
1$
#4950000
0$
0(
#4955000
1$
#4960000
0$
#4965000
1$
#4970000
0$
#4975000
1$
#4980000
0$
#4985000
1$
#4990000
1'
b101 :
b0 ;
0$
1(
#4995000
b101 0
b101000 "
b101000 )
b101000 /
b0 5
13
1$
#5000000
0$
0(
#5005000
14
1$
#5010000
0$
#5015000
1$
#5020000
0$
#5025000
1$
#5030000
0$
#5035000
1$
#5040000
b1 ;
0$
1(
#5045000
b1 5
1$
#5050000
0$
0(
#5055000
1$
#5060000
0$
#5065000
1$
#5070000
0$
#5075000
1$
#5080000
0$
#5085000
1$
#5090000
b10 ;
0$
1(
#5095000
b10 5
1$
#5100000
0$
0(
#5105000
1$
#5110000
0$
#5115000
1$
#5120000
0$
#5125000
1$
#5130000
0$
#5135000
1$
#5140000
b11 ;
0$
1(
#5145000
b11 5
1$
#5150000
0$
0(
#5155000
1$
#5160000
0$
#5165000
1$
#5170000
0$
#5175000
1$
#5180000
0$
#5185000
1$
#5190000
b100 ;
0$
1(
#5195000
b100 5
1$
#5200000
0$
0(
#5205000
1$
#5210000
0$
#5215000
1$
#5220000
0$
#5225000
1$
#5230000
0$
#5235000
1$
#5240000
b101 ;
0$
1(
#5245000
b101 5
1$
#5250000
0$
0(
#5255000
1$
#5260000
0$
#5265000
1$
#5270000
0$
#5275000
1$
#5280000
0$
#5285000
1$
#5290000
b110 ;
0$
1(
#5295000
b110 5
1$
#5300000
0$
0(
#5305000
1$
#5310000
0$
#5315000
1$
#5320000
0$
#5325000
1$
#5330000
0$
#5335000
1$
#5340000
b111 ;
0$
1(
#5345000
b1 6
b111 5
1$
#5350000
0$
0(
#5355000
1$
#5360000
0$
#5365000
1$
#5370000
0$
#5375000
1$
#5380000
0$
#5385000
1$
#5390000
b1000 ;
0$
1(
#5395000
b10 6
b1000 5
1$
#5400000
0$
0(
#5405000
1$
#5410000
0$
#5415000
1$
#5420000
0$
#5425000
1$
#5430000
0$
#5435000
1$
#5440000
b1001 ;
0$
1(
#5445000
b11 6
b1001 5
1$
#5450000
0$
0(
#5455000
1$
#5460000
0$
#5465000
1$
#5470000
0$
#5475000
1$
#5480000
0$
