verilog/index.v
//taps = 16
//order =15

module filter (
    input wire clk,
    input wire rstn,
    input wire signed [7:0] sig,
    output wire signed [19:0] samp_op,
    output wire signed [7:0] trunc_op
);
    
    //assume the sig is q1.7
// Declaration (16 elements, indexed 0 to 15)
wire signed [7:0] coeff [0:15];
reg signed [7:0] signal[0:15];
wire signed [15:0] res[0:15];

// Continuous assignments
assign coeff[0]  = 8'sd0;
assign coeff[1]  = 8'sd5;
assign coeff[2]  = 8'sd4;
assign coeff[3]  = -8'sd5;
assign coeff[4]  = -8'sd10;
assign coeff[5]  = 8'sd0;
assign coeff[6]  = 8'sd24;
assign coeff[7]  = 8'sd45;
assign coeff[8]  = 8'sd45;
assign coeff[9]  = 8'sd24;
assign coeff[10] = 8'sd0;
assign coeff[11] = -8'sd10;
assign coeff[12] = -8'sd5;
assign coeff[13] = 8'sd4;
assign coeff[14] = 8'sd5;
assign coeff[15] = 8'sd0;

integer i;
always @(posedge clk or negedge rstn) begin
    
    if(!rstn) begin
        for(i=0;i<16;i=i+1)begin
            signal[i]<=8'sd0;
        end
    end else begin
        for(i=15;i>0;i=i-1) begin
            signal[i]<=signal[i-1];
        end
        signal[0]<=sig;
    end

end


genvar k;
generate
    
for(k=0;k<16;k=k+1) begin: gen

    mul ml(

        .delsig(signal[k]),
        .coeff(coeff[k]),
        .res(res[k])

    );

end

endgenerate
wire signed [19:0] sum;

assign sum = res[0]  + res[1]  + res[2]  + res[3]  +
             res[4]  + res[5]  + res[6]  + res[7]  +
             res[8]  + res[9]  + res[10] + res[11] +
             res[12] + res[13] + res[14] + res[15];



wire signed [19:0] rounded_sum;
assign rounded_sum = sum + 20'sd64;


wire signed [12:0] scaled_sum;
assign scaled_sum = rounded_sum >>> 7;

reg signed [7:0] final_trunc;

always @(*) begin
    // Positive Overflow: Value > 127
    if (scaled_sum > 13'sd127) begin
        final_trunc = 8'sd127;
    // Negative Overflow: Value < -128
    end else if (scaled_sum < -13'sd128) begin
        final_trunc = -8'sd128;
    // Normal Range: Safely assign low 8 bits
    end else begin
        final_trunc = scaled_sum[7:0];
    end
end

assign samp_op  = sum;
assign trunc_op = final_trunc;


endmodule

module mul(

    input signed [7:0] delsig,
    input signed [7:0] coeff,
    output signed [15:0] res

);

assign res=coeff*delsig;

endmodule

verilog/tb_index.v
`timescale 1ns / 1ps

module tb_index;

    reg clk;
    always #(5.0) clk = ~clk;

    reg rst_n = 1'b0;


    // ---- Shared DUT input signals (reg) ----
    reg rstn;
    reg [7:0] sig;

    // ---- Shared DUT output signals (wire) ----
    wire [19:0] samp_op;
    wire [7:0] trunc_op;
reg signed [7:0] x_input [0:4];
    // ---- DUT: filter (u_filter) ----
    filter u_filter (
        .clk      ( clk      ),
        .rstn     ( rstn     ),
        .sig      ( sig      ),
        .samp_op  ( samp_op  ),
        .trunc_op ( trunc_op ));

    initial begin
        $dumpfile("tb_index.vcd");
        $dumpvars(0, tb_index);
    end
integer i;
    initial begin

        clk=0;
        rstn=0;
        sig=8'sd0;


        x_input[0] = 8'sd1;
        x_input[1] = 8'sd2;
        x_input[2] = 8'sd3;
        x_input[3] = 8'sd4;
        x_input[4] = 8'sd5;


        #15 rstn=1;
// Stream 5 inputs + 1 extra zero sample to flush the last calculation
for (i = 0; i < 20; i = i + 1) begin
    @(posedge clk);
    if (i < 5) 
        sig <= x_input[i];
    else 
        sig <= 8'sd0; // Flush sample

    #1;
    $display("Cycle = %0d | sig = %3d | samp_op = %5d | trunc_op = %5d", i + 1, sig, $signed(samp_op), $signed(trunc_op));
end
        #20;
$finish;
    end

endmodule

verilog/tb_index.vcd
$date
	Fri Sep 11 23:59:28 2026
$end
$version
	Icarus Verilog
$end
$timescale
	1ps
$end
$scope module tb_index $end
$var wire 8 ! trunc_op [7:0] $end
$var wire 20 " samp_op [19:0] $end
$var reg 1 # clk $end
$var reg 1 $ rst_n $end
$var reg 1 % rstn $end
$var reg 8 & sig [7:0] $end
$var integer 32 ' i [31:0] $end
$scope module u_filter $end
$var wire 1 # clk $end
$var wire 1 % rstn $end
$var wire 20 ( samp_op [19:0] $end
$var wire 8 ) sig [7:0] $end
$var wire 8 * trunc_op [7:0] $end
$var wire 20 + sum [19:0] $end
$var wire 13 , scaled_sum [12:0] $end
$var wire 20 - rounded_sum [19:0] $end
$var reg 8 . final_trunc [7:0] $end
$var integer 32 / i [31:0] $end
$scope begin gen[0] $end
$var parameter 2 0 k $end
$scope module ml $end
$var wire 8 1 coeff [7:0] $end
$var wire 8 2 delsig [7:0] $end
$var wire 16 3 res [15:0] $end
$upscope $end
$upscope $end
$scope begin gen[1] $end
$var parameter 2 4 k $end
$scope module ml $end
$var wire 8 5 coeff [7:0] $end
$var wire 8 6 delsig [7:0] $end
$var wire 16 7 res [15:0] $end
$upscope $end
$upscope $end
$scope begin gen[2] $end
$var parameter 3 8 k $end
$scope module ml $end
$var wire 8 9 coeff [7:0] $end
$var wire 8 : delsig [7:0] $end
$var wire 16 ; res [15:0] $end
$upscope $end
$upscope $end
$scope begin gen[3] $end
$var parameter 3 < k $end
$scope module ml $end
$var wire 8 = coeff [7:0] $end
$var wire 8 > delsig [7:0] $end
$var wire 16 ? res [15:0] $end
$upscope $end
$upscope $end
$scope begin gen[4] $end
$var parameter 4 @ k $end
$scope module ml $end
$var wire 8 A coeff [7:0] $end
$var wire 8 B delsig [7:0] $end
$var wire 16 C res [15:0] $end
$upscope $end
$upscope $end
$scope begin gen[5] $end
$var parameter 4 D k $end
$scope module ml $end
$var wire 8 E coeff [7:0] $end
$var wire 8 F delsig [7:0] $end
$var wire 16 G res [15:0] $end
$upscope $end
$upscope $end
$scope begin gen[6] $end
$var parameter 4 H k $end
$scope module ml $end
$var wire 8 I coeff [7:0] $end
$var wire 8 J delsig [7:0] $end
$var wire 16 K res [15:0] $end
$upscope $end
$upscope $end
$scope begin gen[7] $end
$var parameter 4 L k $end
$scope module ml $end
$var wire 8 M coeff [7:0] $end
$var wire 8 N delsig [7:0] $end
$var wire 16 O res [15:0] $end
$upscope $end
$upscope $end
$scope begin gen[8] $end
$var parameter 5 P k $end
$scope module ml $end
$var wire 8 Q coeff [7:0] $end
$var wire 8 R delsig [7:0] $end
$var wire 16 S res [15:0] $end
$upscope $end
$upscope $end
$scope begin gen[9] $end
$var parameter 5 T k $end
$scope module ml $end
$var wire 8 U coeff [7:0] $end
$var wire 8 V delsig [7:0] $end
$var wire 16 W res [15:0] $end
$upscope $end
$upscope $end
$scope begin gen[10] $end
$var parameter 5 X k $end
$scope module ml $end
$var wire 8 Y coeff [7:0] $end
$var wire 8 Z delsig [7:0] $end
$var wire 16 [ res [15:0] $end
$upscope $end
$upscope $end
$scope begin gen[11] $end
$var parameter 5 \ k $end
$scope module ml $end
$var wire 8 ] coeff [7:0] $end
$var wire 8 ^ delsig [7:0] $end
$var wire 16 _ res [15:0] $end
$upscope $end
$upscope $end
$scope begin gen[12] $end
$var parameter 5 ` k $end
$scope module ml $end
$var wire 8 a coeff [7:0] $end
$var wire 8 b delsig [7:0] $end
$var wire 16 c res [15:0] $end
$upscope $end
$upscope $end
$scope begin gen[13] $end
$var parameter 5 d k $end
$scope module ml $end
$var wire 8 e coeff [7:0] $end
$var wire 8 f delsig [7:0] $end
$var wire 16 g res [15:0] $end
$upscope $end
$upscope $end
$scope begin gen[14] $end
$var parameter 5 h k $end
$scope module ml $end
$var wire 8 i coeff [7:0] $end
$var wire 8 j delsig [7:0] $end
$var wire 16 k res [15:0] $end
$upscope $end
$upscope $end
$scope begin gen[15] $end
$var parameter 5 l k $end
$scope module ml $end
$var wire 8 m coeff [7:0] $end
$var wire 8 n delsig [7:0] $end
$var wire 16 o res [15:0] $end
$upscope $end
$upscope $end
$upscope $end
$upscope $end
$enddefinitions $end
$comment Show the parameter values. $end
$dumpall
b1111 l
b1110 h
b1101 d
b1100 `
b1011 \
b1010 X
b1001 T
b1000 P
b111 L
b110 H
b101 D
b100 @
b11 <
b10 8
b1 4
b0 0
$end
#0
$dumpvars
b0 o
b0 n
b0 m
b0 k
b0 j
b101 i
b0 g
b0 f
b100 e
b0 c
b0 b
b11111011 a
b0 _
b0 ^
b11110110 ]
b0 [
b0 Z
b0 Y
b0 W
b0 V
b11000 U
b0 S
b0 R
b101101 Q
b0 O
b0 N
b101101 M
b0 K
b0 J
b11000 I
b0 G
b0 F
b0 E
b0 C
b0 B
b11110110 A
b0 ?
b0 >
b11111011 =
b0 ;
b0 :
b100 9
b0 7
b0 6
b101 5
b0 3
b0 2
b0 1
b10000 /
b0 .
b1000000 -
b0 ,
b0 +
b0 *
b0 )
b0 (
bx '
b0 &
0%
0$
0#
b0 "
b0 !
$end
#5000
b10000 /
1#
#10000
0#
#15000
b1 &
b1 )
b0 /
1#
b0 '
1%
#16000
b1 '
#20000
0#
#25000
b1 2
b10 &
b10 )
b0 /
1#
#26000
b10 '
#30000
0#
#35000
b10 2
b1000101 -
b101 "
b101 (
b101 +
b101 7
b1 6
b11 &
b11 )
b0 /
1#
#36000
b11 '
#40000
0#
#45000
b11 2
b1010 7
b10 6
b1001110 -
b1110 "
b1110 (
b1110 +
b100 ;
b1 :
b100 &
b100 )
b0 /
1#
#46000
b100 '
#50000
0#
#55000
b100 2
b1111 7
b11 6
b1000 ;
b10 :
b1010010 -
b10010 "
b10010 (
b10010 +
b1111111111111011 ?
b1 >
b101 &
b101 )
b0 /
1#
#56000
b101 '
#60000
0#
#65000
b101 2
b10100 7
b100 6
b1100 ;
b11 :
b1111111111110110 ?
b10 >
b1001100 -
b1100 "
b1100 (
b1100 +
b1111111111110110 C
b1 B
b0 &
b0 )
b0 /
1#
#66000
b110 '
#70000
0#
#75000
b0 2
b11001 7
b101 6
b10000 ;
b100 :
b1111111111110001 ?
b11 >
b1000110 -
b110 "
b110 (
b110 +
b1111111111101100 C
b10 B
b1 F
b0 /
1#
#76000
b111 '
#80000
0#
#85000
b0 7
b0 6
b10100 ;
b101 :
b1111111111101100 ?
b100 >
b1111111111100010 C
b11 B
b10 F
b111010 -
b11111111111111111010 "
b11111111111111111010 (
b11111111111111111010 +
b11000 K
b1 J
b0 /
1#
#86000
b1000 '
#90000
0#
#95000
b0 ;
b0 :
b1111111111100111 ?
b101 >
b1111111111011000 C
b100 B
b11 F
b110000 K
b10 J
b1011100 -
b11100 "
b11100 (
b11100 +
b101101 O
b1 N
b0 /
1#
#96000
b1001 '
#100000
0#
#105000
b1 !
b1 *
b1 .
b1 ,
b0 ?
b0 >
b1111111111001110 C
b101 B
b100 F
b1001000 K
b11 J
b1011010 O
b10 N
b11011101 -
b10011101 "
b10011101 (
b10011101 +
b101101 S
b1 R
b0 /
1#
#106000
b1010 '
#110000
0#
#115000
b11 !
b11 *
b11 .
b11 ,
b0 C
b0 B
b101 F
b1100000 K
b100 J
b10000111 O
b11 N
b1011010 S
b10 R
b110011001 -
b101011001 "
b101011001 (
b101011001 +
b11000 W
b1 V
b0 /
1#
#116000
b1011 '
#120000
0#
#125000
b100 !
b100 *
b100 .
b100 ,
b0 F
b1111000 K
b101 J
b10110100 O
b100 N
b10000111 S
b11 R
b1000100011 -
b111100011 "
b111100011 (
b111100011 +
b110000 W
b10 V
b1 Z
b0 /
1#
#126000
b1100 '
#130000
0#
#135000
b0 K
b0 J
b11100001 O
b101 N
b10110100 S
b100 R
b1001000 W
b11 V
b10 Z
b1000010011 -
b111010011 "
b111010011 (
b111010011 +
b1111111111110110 _
b1 ^
b0 /
1#
#136000
b1101 '
#140000
0#
#145000
b10 !
b10 *
b10 .
b10 ,
b0 O
b0 N
b11100001 S
b101 R
b1100000 W
b100 V
b11 Z
b1111111111101100 _
b10 ^
b101101000 -
b100101000 "
b100101000 (
b100101000 +
b1111111111111011 c
b1 b
b0 /
1#
#146000
b1110 '
#150000
0#
#155000
b1 !
b1 *
b1 .
b1 ,
b0 S
b0 R
b1111000 W
b101 V
b100 Z
b1111111111100010 _
b11 ^
b1111111111110110 c
b10 b
b10010100 -
b1010100 "
b1010100 (
b1010100 +
b100 g
b1 f
b0 /
1#
#156000
b1111 '
#160000
0#
#165000
b0 !
b0 *
b0 .
b0 ,
b0 W
b0 V
b101 Z
b1111111111011000 _
b100 ^
b1111111111110001 c
b11 b
b1000 g
b10 f
b10110 -
b11111111111111010110 "
b11111111111111010110 (
b11111111111111010110 +
b101 k
b1 j
b0 /
1#
#166000
b10000 '
#170000
0#
#175000
b0 Z
b1111111111001110 _
b101 ^
b1111111111101100 c
b100 b
b1100 g
b11 f
b10000 -
b11111111111111010000 "
b11111111111111010000 (
b11111111111111010000 +
b1010 k
b10 j
b1 n
b0 /
1#
#176000
b10001 '
#180000
0#
#185000
b0 _
b0 ^
b1111111111100111 c
b101 b
b10000 g
b100 f
b1000110 -
b110 "
b110 (
b110 +
b1111 k
b11 j
b10 n
b0 /
1#
#186000
b10010 '
#190000
0#
#195000
b0 c
b0 b
b10100 g
b101 f
b1101000 -
b101000 "
b101000 (
b101000 +
b10100 k
b100 j
b11 n
b0 /
1#
#196000
b10011 '
#200000
0#
#205000
b0 g
b0 f
b1011001 -
b11001 "
b11001 (
b11001 +
b11001 k
b101 j
b100 n
b0 /
1#
#206000
b10100 '
#210000
0#
#215000
b1000000 -
b0 "
b0 (
b0 +
b0 k
b0 j
b101 n
b0 /
1#
#220000
0#
#225000
b0 n
b0 /
1#
