verilog/fir_filter/index.v
//taps = 16
//order =15

module filter (
    input wire clk,
    input wire rstn,
    input wire signed [7:0] sig,
    output wire signed [19:0] samp_op,
    output wire signed [7:0] trunc_op
);
    
    //assume the sig is q1.7

wire signed [7:0] coeff [0:15];
reg signed [7:0] signal[0:15];
wire signed [15:0] res[0:15];


assign coeff[0]  = 8'sd0;
assign coeff[1]  = 8'sd5;
assign coeff[2]  = 8'sd4;
assign coeff[3]  = -8'sd5;
assign coeff[4]  = -8'sd10;
assign coeff[5]  = 8'sd0;
assign coeff[6]  = 8'sd24;
assign coeff[7]  = 8'sd45;
assign coeff[8]  = 8'sd45;
assign coeff[9]  = 8'sd24;
assign coeff[10] = 8'sd0;
assign coeff[11] = -8'sd10;
assign coeff[12] = -8'sd5;
assign coeff[13] = 8'sd4;
assign coeff[14] = 8'sd5;
assign coeff[15] = 8'sd0;

integer i;
always @(posedge clk or negedge rstn) begin
    
    if(!rstn) begin
        for(i=0;i<16;i=i+1)begin
            signal[i]<=8'sd0;
        end
    end else begin
        for(i=15;i>0;i=i-1) begin
            signal[i]<=signal[i-1];
        end
        signal[0]<=sig;
    end

end


genvar k;
generate
    
for(k=0;k<16;k=k+1) begin: gen

    mul ml(

        .delsig(signal[k]),
        .coeff(coeff[k]),
        .res(res[k])

    );

end

endgenerate
wire signed [19:0] sum;

assign sum = res[0]  + res[1]  + res[2]  + res[3]  +
             res[4]  + res[5]  + res[6]  + res[7]  +
             res[8]  + res[9]  + res[10] + res[11] +
             res[12] + res[13] + res[14] + res[15];



wire signed [19:0] rounded_sum;
assign rounded_sum = sum + 20'sd64;


wire signed [12:0] scaled_sum;
assign scaled_sum = rounded_sum >>> 7;

reg signed [7:0] final_trunc;

always @(*) begin
   
    if (scaled_sum > 13'sd127) begin
        final_trunc = 8'sd127;

    end else if (scaled_sum < -13'sd128) begin
        final_trunc = -8'sd128;

    end else begin
        final_trunc = scaled_sum[7:0];
    end
end

assign samp_op  = sum;
assign trunc_op = final_trunc;


endmodule

module mul(

    input signed [7:0] delsig,
    input signed [7:0] coeff,
    output signed [15:0] res

);

assign res=coeff*delsig;

endmodule

verilog/fir_filter/tb_index.v
`timescale 1ns / 1ps

module tb_index;

    reg clk;
    always #(5.0) clk = ~clk;

    reg rst_n = 1'b0;


    // ---- Shared DUT input signals (reg) ----
    reg rstn;
    reg [7:0] sig;

    // ---- Shared DUT output signals (wire) ----
    wire [19:0] samp_op;
    wire [7:0] trunc_op;
reg signed [7:0] x_input [0:4];
    // ---- DUT: filter (u_filter) ----
    filter u_filter (
        .clk      ( clk      ),
        .rstn     ( rstn     ),
        .sig      ( sig      ),
        .samp_op  ( samp_op  ),
        .trunc_op ( trunc_op ));

    initial begin
        $dumpfile("tb_index.vcd");
        $dumpvars(0, tb_index);
    end
integer i;
    initial begin

        clk=0;
        rstn=0;
        sig=8'sd0;


        x_input[0] = 8'sd60;
        x_input[1] = 8'sd70;
        x_input[2] = 8'sd80;
        x_input[3] = 8'sd90;
        x_input[4] = 8'sd100;


        #15 rstn=1;

for (i = 0; i < 21; i = i + 1) begin
    @(posedge clk);
    if (i < 5) 
        sig <= x_input[i];
    else 
        sig <= 8'sd0; 

    #1;
    $display("cycle = %d  sig = %d  samp_op = %d  trunc_op = %d", i + 1, sig, $signed(samp_op), $signed(trunc_op));
end
        #20;
$finish;
    end

endmodule

verilog/fir_filter/tb_index.vcd
$date
	Mon Sep 14 21:14:39 2026
$end
$version
	Icarus Verilog
$end
$timescale
	1ps
$end
$scope module tb_index $end
$var wire 8 ! trunc_op [7:0] $end
$var wire 20 " samp_op [19:0] $end
$var reg 1 # clk $end
$var reg 1 $ rst_n $end
$var reg 1 % rstn $end
$var reg 8 & sig [7:0] $end
$var integer 32 ' i [31:0] $end
$scope module u_filter $end
$var wire 1 # clk $end
$var wire 1 % rstn $end
$var wire 20 ( samp_op [19:0] $end
$var wire 8 ) sig [7:0] $end
$var wire 8 * trunc_op [7:0] $end
$var wire 20 + sum [19:0] $end
$var wire 13 , scaled_sum [12:0] $end
$var wire 20 - rounded_sum [19:0] $end
$var reg 8 . final_trunc [7:0] $end
$var integer 32 / i [31:0] $end
$scope begin gen[0] $end
$var parameter 2 0 k $end
$scope module ml $end
$var wire 8 1 coeff [7:0] $end
$var wire 8 2 delsig [7:0] $end
$var wire 16 3 res [15:0] $end
$upscope $end
$upscope $end
$scope begin gen[1] $end
$var parameter 2 4 k $end
$scope module ml $end
$var wire 8 5 coeff [7:0] $end
$var wire 8 6 delsig [7:0] $end
$var wire 16 7 res [15:0] $end
$upscope $end
$upscope $end
$scope begin gen[2] $end
$var parameter 3 8 k $end
$scope module ml $end
$var wire 8 9 coeff [7:0] $end
$var wire 8 : delsig [7:0] $end
$var wire 16 ; res [15:0] $end
$upscope $end
$upscope $end
$scope begin gen[3] $end
$var parameter 3 < k $end
$scope module ml $end
$var wire 8 = coeff [7:0] $end
$var wire 8 > delsig [7:0] $end
$var wire 16 ? res [15:0] $end
$upscope $end
$upscope $end
$scope begin gen[4] $end
$var parameter 4 @ k $end
$scope module ml $end
$var wire 8 A coeff [7:0] $end
$var wire 8 B delsig [7:0] $end
$var wire 16 C res [15:0] $end
$upscope $end
$upscope $end
$scope begin gen[5] $end
$var parameter 4 D k $end
$scope module ml $end
$var wire 8 E coeff [7:0] $end
$var wire 8 F delsig [7:0] $end
$var wire 16 G res [15:0] $end
$upscope $end
$upscope $end
$scope begin gen[6] $end
$var parameter 4 H k $end
$scope module ml $end
$var wire 8 I coeff [7:0] $end
$var wire 8 J delsig [7:0] $end
$var wire 16 K res [15:0] $end
$upscope $end
$upscope $end
$scope begin gen[7] $end
$var parameter 4 L k $end
$scope module ml $end
$var wire 8 M coeff [7:0] $end
$var wire 8 N delsig [7:0] $end
$var wire 16 O res [15:0] $end
$upscope $end
$upscope $end
$scope begin gen[8] $end
$var parameter 5 P k $end
$scope module ml $end
$var wire 8 Q coeff [7:0] $end
$var wire 8 R delsig [7:0] $end
$var wire 16 S res [15:0] $end
$upscope $end
$upscope $end
$scope begin gen[9] $end
$var parameter 5 T k $end
$scope module ml $end
$var wire 8 U coeff [7:0] $end
$var wire 8 V delsig [7:0] $end
$var wire 16 W res [15:0] $end
$upscope $end
$upscope $end
$scope begin gen[10] $end
$var parameter 5 X k $end
$scope module ml $end
$var wire 8 Y coeff [7:0] $end
$var wire 8 Z delsig [7:0] $end
$var wire 16 [ res [15:0] $end
$upscope $end
$upscope $end
$scope begin gen[11] $end
$var parameter 5 \ k $end
$scope module ml $end
$var wire 8 ] coeff [7:0] $end
$var wire 8 ^ delsig [7:0] $end
$var wire 16 _ res [15:0] $end
$upscope $end
$upscope $end
$scope begin gen[12] $end
$var parameter 5 ` k $end
$scope module ml $end
$var wire 8 a coeff [7:0] $end
$var wire 8 b delsig [7:0] $end
$var wire 16 c res [15:0] $end
$upscope $end
$upscope $end
$scope begin gen[13] $end
$var parameter 5 d k $end
$scope module ml $end
$var wire 8 e coeff [7:0] $end
$var wire 8 f delsig [7:0] $end
$var wire 16 g res [15:0] $end
$upscope $end
$upscope $end
$scope begin gen[14] $end
$var parameter 5 h k $end
$scope module ml $end
$var wire 8 i coeff [7:0] $end
$var wire 8 j delsig [7:0] $end
$var wire 16 k res [15:0] $end
$upscope $end
$upscope $end
$scope begin gen[15] $end
$var parameter 5 l k $end
$scope module ml $end
$var wire 8 m coeff [7:0] $end
$var wire 8 n delsig [7:0] $end
$var wire 16 o res [15:0] $end
$upscope $end
$upscope $end
$upscope $end
$upscope $end
$enddefinitions $end
$comment Show the parameter values. $end
$dumpall
b1111 l
b1110 h
b1101 d
b1100 `
b1011 \
b1010 X
b1001 T
b1000 P
b111 L
b110 H
b101 D
b100 @
b11 <
b10 8
b1 4
b0 0
$end
#0
$dumpvars
b0 o
b0 n
b0 m
b0 k
b0 j
b101 i
b0 g
b0 f
b100 e
b0 c
b0 b
b11111011 a
b0 _
b0 ^
b11110110 ]
b0 [
b0 Z
b0 Y
b0 W
b0 V
b11000 U
b0 S
b0 R
b101101 Q
b0 O
b0 N
b101101 M
b0 K
b0 J
b11000 I
b0 G
b0 F
b0 E
b0 C
b0 B
b11110110 A
b0 ?
b0 >
b11111011 =
b0 ;
b0 :
b100 9
b0 7
b0 6
b101 5
b0 3
b0 2
b0 1
b10000 /
b0 .
b1000000 -
b0 ,
b0 +
b0 *
b0 )
b0 (
bx '
b0 &
0%
0$
0#
b0 "
b0 !
$end
#5000
b10000 /
1#
#10000
0#
#15000
b111100 &
b111100 )
b0 /
1#
b0 '
1%
#16000
b1 '
#20000
0#
#25000
b111100 2
b1000110 &
b1000110 )
b0 /
1#
#26000
b10 '
#30000
0#
#35000
b10 !
b10 *
b10 .
b10 ,
b1000110 2
b101101100 -
b100101100 "
b100101100 (
b100101100 +
b100101100 7
b111100 6
b1010000 &
b1010000 )
b0 /
1#
#36000
b11 '
#40000
0#
#45000
b101 !
b101 *
b101 .
b101 ,
b1010000 2
b101011110 7
b1000110 6
b1010001110 -
b1001001110 "
b1001001110 (
b1001001110 +
b11110000 ;
b111100 :
b1011010 &
b1011010 )
b0 /
1#
#46000
b100 '
#50000
0#
#55000
b11 !
b11 *
b11 .
b11 ,
b1011010 2
b110010000 7
b1010000 6
b100011000 ;
b1000110 :
b110111100 -
b101111100 "
b101111100 (
b101111100 +
b1111111011010100 ?
b111100 >
b1100100 &
b1100100 )
b0 /
1#
#56000
b101 '
#60000
0#
#65000
b11111111 !
b11111111 *
b11111111 .
b1111111111111 ,
b1100100 2
b111000010 7
b1011010 6
b101000000 ;
b1010000 :
b1111111010100010 ?
b1000110 >
b11111111111110001100 -
b11111111111101001100 "
b11111111111101001100 (
b11111111111101001100 +
b1111110110101000 C
b111100 B
b0 &
b0 )
b0 /
1#
#66000
b110 '
#70000
0#
#75000
b11111110 !
b11111110 *
b11111110 .
b1111111111110 ,
b0 2
b111110100 7
b1100100 6
b101101000 ;
b1011010 :
b1111111001110000 ?
b1010000 >
b11111111111101010000 -
b11111111111100010000 "
b11111111111100010000 (
b11111111111100010000 +
b1111110101000100 C
b1000110 B
b111100 F
b0 /
1#
#76000
b111 '
#80000
0#
#85000
b101 !
b101 *
b101 .
b101 ,
b0 7
b0 6
b110010000 ;
b1100100 :
b1111111000111110 ?
b1011010 >
b1111110011100000 C
b1010000 B
b1000110 F
b1010001110 -
b1001001110 "
b1001001110 (
b1001001110 +
b10110100000 K
b111100 J
b0 /
1#
#86000
b1000 '
#90000
0#
#95000
b10111 !
b10111 *
b10111 .
b10111 ,
b0 ;
b0 :
b1111111000001100 ?
b1100100 >
b1111110001111100 C
b1011010 B
b1010000 F
b11010010000 K
b1000110 J
b101111100100 -
b101110100100 "
b101110100100 (
b101110100100 +
b101010001100 O
b111100 N
b0 /
1#
#96000
b1001 '
#100000
0#
#105000
b110101 !
b110101 *
b110101 .
b110101 ,
b0 ?
b0 >
b1111110000011000 C
b1100100 B
b1011010 F
b11110000000 K
b1010000 J
b110001001110 O
b1000110 N
b1101010110010 -
b1101001110010 "
b1101001110010 (
b1101001110010 +
b101010001100 S
b111100 R
b0 /
1#
#106000
b1010 '
#110000
0#
#115000
b1010001 !
b1010001 *
b1010001 .
b1010001 ,
b0 C
b0 B
b1100100 F
b100001110000 K
b1011010 J
b111000010000 O
b1010000 N
b110001001110 S
b1000110 R
b10100010101110 -
b10100001101110 "
b10100001101110 (
b10100001101110 +
b10110100000 W
b111100 V
b0 /
1#
#116000
b1011 '
#120000
0#
#125000
b1011100 !
b1011100 *
b1011100 .
b1011100 ,
b0 F
b100101100000 K
b1100100 J
b111111010010 O
b1011010 N
b111000010000 S
b1010000 R
b10111000010010 -
b10110111010010 "
b10110111010010 (
b10110111010010 +
b11010010000 W
b1000110 V
b111100 Z
b0 /
1#
#126000
b1100 '
#130000
0#
#135000
b1001101 !
b1001101 *
b1001101 .
b1001101 ,
b0 K
b0 J
b1000110010100 O
b1100100 N
b111111010010 S
b1011010 R
b11110000000 W
b1010000 V
b1000110 Z
b10011011001110 -
b10011010001110 "
b10011010001110 (
b10011010001110 +
b1111110110101000 _
b111100 ^
b0 /
1#
#136000
b1101 '
#140000
0#
#145000
b101100 !
b101100 *
b101100 .
b101100 ,
b0 O
b0 N
b1000110010100 S
b1100100 R
b100001110000 W
b1011010 V
b1010000 Z
b1111110101000100 _
b1000110 ^
b1011001011100 -
b1011000011100 "
b1011000011100 (
b1011000011100 +
b1111111011010100 c
b111100 b
b0 /
1#
#146000
b1110 '
#150000
0#
#155000
b1100 !
b1100 *
b1100 .
b1100 ,
b0 S
b0 R
b100101100000 W
b1100100 V
b1011010 Z
b1111110011100000 _
b1010000 ^
b1111111010100010 c
b1000110 b
b11000010010 -
b10111010010 "
b10111010010 (
b10111010010 +
b11110000 g
b111100 f
b0 /
1#
#156000
b1111 '
#160000
0#
#165000
b11111010 !
b11111010 *
b11111010 .
b1111111111010 ,
b0 W
b0 V
b1100100 Z
b1111110001111100 _
b1011010 ^
b1111111001110000 c
b1010000 b
b100011000 g
b1000110 f
b11111111110101110000 -
b11111111110100110000 "
b11111111110100110000 (
b11111111110100110000 +
b100101100 k
b111100 j
b0 /
1#
#166000
b10000 '
#170000
0#
#175000
b0 Z
b1111110000011000 _
b1100100 ^
b1111111000111110 c
b1011010 b
b101000000 g
b1010000 f
b11111111110100110100 -
b11111111110011110100 "
b11111111110011110100 (
b11111111110011110100 +
b101011110 k
b1000110 j
b111100 n
b0 /
1#
#176000
b10001 '
#180000
0#
#185000
b10 !
b10 *
b10 .
b10 ,
b0 _
b0 ^
b1111111000001100 c
b1100100 b
b101101000 g
b1011010 f
b101000100 -
b100000100 "
b100000100 (
b100000100 +
b110010000 k
b1010000 j
b1000110 n
b0 /
1#
#186000
b10010 '
#190000
0#
#195000
b111 !
b111 *
b111 .
b111 ,
b0 c
b0 b
b110010000 g
b1100100 f
b1110010010 -
b1101010010 "
b1101010010 (
b1101010010 +
b111000010 k
b1011010 j
b1010000 n
b0 /
1#
#196000
b10011 '
#200000
0#
#205000
b100 !
b100 *
b100 .
b100 ,
b0 g
b0 f
b1000110100 -
b111110100 "
b111110100 (
b111110100 +
b111110100 k
b1100100 j
b1011010 n
b0 /
1#
#206000
b10100 '
#210000
0#
#215000
b0 !
b0 *
b0 .
b0 ,
b1000000 -
b0 "
b0 (
b0 +
b0 k
b0 j
b1100100 n
b0 /
1#
#216000
b10101 '
#220000
0#
#225000
b0 n
b0 /
1#
#230000
0#
#235000
b0 /
1#
